{
  "posts": [
    {
      "id": 1,
      "title": "Post 1"
    },
    {
      "id": 2,
      "title": "Post 2"
    },
    {
      "id": 3,
      "title": "Post 3"
    }
  ],
  "comments": [
    {
      "id": 1,
      "body": "some comment",
      "postId": 1
    },
    {
      "id": 2,
      "body": "some comment",
      "postId": 1
    }
  ],
  "profile": {
    "name": "typicode"
  },
  "zones": [
    {
      "id": 0,
      "name": "Rest of the World",
      "order": 0,
      "_links": {
        "self": [
          {
            "href": "https://example.com/wp-json/wc/v3/shipping/zones/0"
          }
        ],
        "collection": [
          {
            "href": "https://example.com/wp-json/wc/v3/shipping/zones"
          }
        ],
        "describedby": [
          {
            "href": "https://example.com/wp-json/wc/v3/shipping/zones/0/locations"
          }
        ]
      }
    },
    {
      "id": 5,
      "name": "Brazil",
      "order": 0,
      "_links": {
        "self": [
          {
            "href": "https://example.com/wp-json/wc/v3/shipping/zones/5"
          }
        ],
        "collection": [
          {
            "href": "https://example.com/wp-json/wc/v3/shipping/zones"
          }
        ],
        "describedby": [
          {
            "href": "https://example.com/wp-json/wc/v3/shipping/zones/5/locations"
          }
        ]
      }
    }
  ]
}